yaoys_checkin/AutoCheckIn.py
yaoys_checkin/AutoCheckinService.py
yaoys_checkin/__init__.py
yaoys_checkin/__version__.py
yaoys_checkin/ablesci_checkin/__init__.py
yaoys_checkin/ablesci_checkin/ableSci_checkin.py
yaoys_checkin/aliyunpan_checkin/__init__.py
yaoys_checkin/aliyunpan_checkin/aliyunpan_checkin.py
yaoys_checkin/aliyunpan_checkin/aliyunpan_task/__init__.py
yaoys_checkin/aliyunpan_checkin/aliyunpan_task/alipan_utils.py
yaoys_checkin/aliyunpan_checkin/aliyunpan_task/aliyunpan_task.py
yaoys_checkin/bilibili_checkin/__init__.py
yaoys_checkin/bilibili_checkin/bilibili_alive_auto_checkin.py
yaoys_checkin/bilibili_checkin/bilibili_auto_checkin.py
yaoys_checkin/checkin_util/__init__.py
yaoys_checkin/checkin_util/check_version_util.py
yaoys_checkin/checkin_util/checkin_class.py
yaoys_checkin/checkin_util/checkin_log.py
yaoys_checkin/checkin_util/common_util.py
yaoys_checkin/checkin_util/constants.py
yaoys_checkin/checkin_util/logutil.py
yaoys_checkin/checkin_util/uc_driver.py
yaoys_checkin/cloud_189_checkin/1.py
yaoys_checkin/cloud_189_checkin/__init__.py
yaoys_checkin/cloud_189_checkin/cloud189_checkin.py
yaoys_checkin/glados_checkin/__init__.py
yaoys_checkin/glados_checkin/glados.py
yaoys_checkin/gufenxueshu_checkin/__init__.py
yaoys_checkin/gufenxueshu_checkin/gufen_checkin.py
yaoys_checkin/hifini_checkin/__init__.py
yaoys_checkin/hifini_checkin/hifini_autoCheckin.py
yaoys_checkin/jiaoyimao/__init__.py
yaoys_checkin/jiaoyimao/jiaoyimao_checkin.py
yaoys_checkin/kuake_checkin/__init__.py
yaoys_checkin/kuake_checkin/kuakepan_checkin.py
yaoys_checkin/legado/__init__.py
yaoys_checkin/legado/legado_checkin.py
yaoys_checkin/model/__init__.py
yaoys_checkin/model/all_class_parent.py
yaoys_checkin/model/config_file_class.py
yaoys_checkin/model/cookieOrUser_class.py
yaoys_checkin/piaoyunge/__init__.py
yaoys_checkin/piaoyunge/piaoyunge_checkin.py
yaoys_checkin/piaoyunge/piaoyunge_checkin_1.py
yaoys_checkin/piaoyunge/piaoyunge_checkin_获取fromhash.py
autodailycheckin-0.1.24.dist-info/LICENSE
autodailycheckin-0.1.24.dist-info/METADATA
autodailycheckin-0.1.24.dist-info/WHEEL
autodailycheckin-0.1.24.dist-info/entry_points.txt
autodailycheckin-0.1.24.dist-info/top_level.txt
autodailycheckin-0.1.24.dist-info/RECORD
