Metadata-Version: 2.1
Name: autodailycheckin
Version: 0.1.24
Summary: yaoys_checkin
Home-page: https://github.com/yaoysyao/Auto_checkin_release
Author: Yaoys
Author-email: yys9508@qq.com
License: MIT
Project-URL: Documentation, https://github.com/yaoysyao/Auto_checkin_release
Classifier: License :: OSI Approved :: MIT License
Classifier: Programming Language :: Python :: 3.8
Classifier: Programming Language :: Python :: 3.9
Classifier: Programming Language :: Python :: 3.10
Classifier: Programming Language :: Python :: Implementation :: CPython
Classifier: Programming Language :: Python :: Implementation :: PyPy
Requires-Python: >=3.8.0
License-File: LICENSE
Requires-Dist: undetected-chromedriver ==3.1.7
Requires-Dist: urllib3 ==1.26.11
Requires-Dist: requests ==2.28.1
Requires-Dist: selenium ==4.3.0
Requires-Dist: bs4 ==0.0.1
Requires-Dist: beautifulsoup4 ==4.11.1
Requires-Dist: APScheduler ~=3.10.1
Requires-Dist: rsa ==4.8
Requires-Dist: colorlog ==6.7.0
Requires-Dist: func-timeout ==4.3.5
Requires-Dist: aligo ==6.1.14
Requires-Dist: m3u8 ==3.5.0
Requires-Dist: pillow ==10.0.0
Requires-Dist: setuptools ==68.0.0
Requires-Dist: ecdsa ==0.18.0
